gotolibr/__init__.py
gotolibr/module.py
gotolibr-1.0.dist-info/LICENSE
gotolibr-1.0.dist-info/METADATA
gotolibr-1.0.dist-info/WHEEL
gotolibr-1.0.dist-info/top_level.txt
gotolibr-1.0.dist-info/RECORD
