Metadata-Version: 2.1
Name: gotolibr
Version: 1.0
Summary: A simple library that allows you to use goto in Python
Author: scientificworld
Maintainer: scientificworld
License: This is free and unencumbered software released into the public domain.
Project-URL: Homepage, https://github.com/scientificworld/gotolibr
Project-URL: Repository, https://github.com/scientificworld/gotolibr.git
Project-URL: Issues, https://github.com/scientificworld/gotolibr/issues
Classifier: Development Status :: 5 - Production/Stable
Classifier: Programming Language :: Python :: 3
Classifier: License :: OSI Approved :: The Unlicense (Unlicense)
Classifier: Operating System :: OS Independent
Requires-Python: >=3.14
License-File: LICENSE
